djangorestframework_simplejwt_captcha2-0.0.9.dist-info/licenses/LICENSE.txt
rest_framework_simplejwt/__init__.py
rest_framework_simplejwt/authentication.py
rest_framework_simplejwt/backends.py
rest_framework_simplejwt/exceptions.py
rest_framework_simplejwt/models.py
rest_framework_simplejwt/py.typed
rest_framework_simplejwt/serializers.py
rest_framework_simplejwt/settings.py
rest_framework_simplejwt/state.py
rest_framework_simplejwt/tokens.py
rest_framework_simplejwt/utils.py
rest_framework_simplejwt/views.py
rest_framework_simplejwt/locale/ar/LC_MESSAGES/django.mo
rest_framework_simplejwt/locale/ar/LC_MESSAGES/django.po
rest_framework_simplejwt/locale/cs/LC_MESSAGES/django.mo
rest_framework_simplejwt/locale/cs/LC_MESSAGES/django.po
rest_framework_simplejwt/locale/de/LC_MESSAGES/django.mo
rest_framework_simplejwt/locale/de/LC_MESSAGES/django.po
rest_framework_simplejwt/locale/es/LC_MESSAGES/django.mo
rest_framework_simplejwt/locale/es/LC_MESSAGES/django.po
rest_framework_simplejwt/locale/es_AR/LC_MESSAGES/django.mo
rest_framework_simplejwt/locale/es_AR/LC_MESSAGES/django.po
rest_framework_simplejwt/locale/es_CL/LC_MESSAGES/django.mo
rest_framework_simplejwt/locale/es_CL/LC_MESSAGES/django.po
rest_framework_simplejwt/locale/fa/LC_MESSAGES/django.mo
rest_framework_simplejwt/locale/fa/LC_MESSAGES/django.po
rest_framework_simplejwt/locale/fa_IR/LC_MESSAGES/django.mo
rest_framework_simplejwt/locale/fa_IR/LC_MESSAGES/django.po
rest_framework_simplejwt/locale/fr/LC_MESSAGES/django.mo
rest_framework_simplejwt/locale/fr/LC_MESSAGES/django.po
rest_framework_simplejwt/locale/he_IL/LC_MESSAGES/django.mo
rest_framework_simplejwt/locale/he_IL/LC_MESSAGES/django.po
rest_framework_simplejwt/locale/id_ID/LC_MESSAGES/django.mo
rest_framework_simplejwt/locale/id_ID/LC_MESSAGES/django.po
rest_framework_simplejwt/locale/it_IT/LC_MESSAGES/django.mo
rest_framework_simplejwt/locale/it_IT/LC_MESSAGES/django.po
rest_framework_simplejwt/locale/ko_KR/LC_MESSAGES/django.mo
rest_framework_simplejwt/locale/ko_KR/LC_MESSAGES/django.po
djangorestframework_simplejwt_captcha2-0.0.9.dist-info/METADATA
djangorestframework_simplejwt_captcha2-0.0.9.dist-info/WHEEL
djangorestframework_simplejwt_captcha2-0.0.9.dist-info/top_level.txt
djangorestframework_simplejwt_captcha2-0.0.9.dist-info/RECORD
