Metadata-Version: 2.4
Name: djangorestframework_simplejwt_captcha2
Version: 0.0.9
Summary: A minimal JSON Web Token authentication plugin for Django REST Framework
Home-page: https://github.com/yaohua1179/djangorestframework_simplejwt_captcha2
Author: Qinghua.yao
Author-email: yaohua1179@163.com
License: MIT
Keywords: djangorestframework_simplejwt_captcha2
Classifier: Development Status :: 5 - Production/Stable
Classifier: Environment :: Web Environment
Classifier: Framework :: Django
Classifier: Framework :: Django :: 4.2
Classifier: Framework :: Django :: 5.0
Classifier: Framework :: Django :: 5.1
Classifier: Framework :: Django :: 5.2
Classifier: Intended Audience :: Developers
Classifier: License :: OSI Approved :: MIT License
Classifier: Operating System :: OS Independent
Classifier: Programming Language :: Python
Classifier: Programming Language :: Python :: 3
Classifier: Programming Language :: Python :: 3.9
Classifier: Programming Language :: Python :: 3.10
Classifier: Programming Language :: Python :: 3.11
Classifier: Programming Language :: Python :: 3.12
Classifier: Programming Language :: Python :: 3.13
Classifier: Topic :: Internet :: WWW/HTTP
Requires-Python: >=3.9
License-File: LICENSE.txt
Requires-Dist: django>=4.2
Requires-Dist: djangorestframework>=3.14
Requires-Dist: pyjwt<2.10.0,>=1.7.1
Requires-Dist: captcha>=0.7.0
Requires-Dist: pillow
Dynamic: author
Dynamic: author-email
Dynamic: classifier
Dynamic: description
Dynamic: home-page
Dynamic: keywords
Dynamic: license
Dynamic: license-file
Dynamic: requires-dist
Dynamic: requires-python
Dynamic: summary
